schematec.contrib-0.1.9-py2.7-nspkg.pth
schematec/contrib/__init__.py
schematec/contrib/datetime.py
schematec.contrib-0.1.9.dist-info/DESCRIPTION.rst
schematec.contrib-0.1.9.dist-info/METADATA
schematec.contrib-0.1.9.dist-info/metadata.json
schematec.contrib-0.1.9.dist-info/namespace_packages.txt
schematec.contrib-0.1.9.dist-info/RECORD
schematec.contrib-0.1.9.dist-info/top_level.txt
schematec.contrib-0.1.9.dist-info/WHEEL
