Metadata-Version: 2.0
Name: schematec.contrib
Version: 0.1.9
Summary: Schematec contrib package
Home-page: https://github.com/mylokin/schematec.contrib
Author: Andrey Gubarev
Author-email: mylokin@me.com
License: MIT
Keywords: schema
Platform: UNKNOWN
Classifier: Development Status :: 4 - Beta
Classifier: Intended Audience :: Developers
Classifier: Operating System :: OS Independent
Classifier: License :: OSI Approved :: MIT License
Classifier: Programming Language :: Python
Classifier: Programming Language :: Python :: 2.7
Classifier: Topic :: Database
Classifier: Topic :: Database :: Database Engines/Servers
